tbcp_gitpy/__init__.py
tbcp_gitpy/branches.py
tbcp_gitpy/commits.py
tbcp_gitpy/config.py
tbcp_gitpy/files.py
tbcp_gitpy/heads.py
tbcp_gitpy/helpers/__init__.py
tbcp_gitpy/helpers/_defaults.py
tbcp_gitpy/index.py
tbcp_gitpy/references.py
tbcp_gitpy/repository.py
tbcp_gitpy/submodule.py
tbcp_gitpy/tags.py
tbcp_gitpy/tree.py
tbcp_gitpy-1.0.1.dist-info/LICENSE
tbcp_gitpy-1.0.1.dist-info/WHEEL
tbcp_gitpy-1.0.1.dist-info/METADATA
tbcp_gitpy-1.0.1.dist-info/RECORD
