Metadata-Version: 2.1
Name: tbcp-gitpy
Version: 1.0.1
Summary: Workiing with Git in Python
Home-page: https://gitlab.com/the-bootcamp-project/packages/gitpy
License: MIT
Keywords: Git,Python
Author: Bootcamp contributors
Author-email: contributors@bootcamp-project.com
Maintainer: Bootcamp contributors
Maintainer-email: contributors@bootcamp-project.com
Requires-Python: >=3.8,<4.0
Classifier: License :: OSI Approved :: MIT License
Classifier: Programming Language :: Python :: 3
Classifier: Programming Language :: Python :: 3.10
Classifier: Programming Language :: Python :: 3.8
Classifier: Programming Language :: Python :: 3.9
Classifier: Topic :: Software Development :: Build Tools
Classifier: Topic :: Software Development :: Libraries :: Python Modules
Requires-Dist: GitPython (>=3.1.24,<4.0.0)
Project-URL: Bug Tracker, https://gitlab.com/the-bootcamp-project/packages/gitpy/-/issues
Project-URL: Bootcamp, https://bootcamp-project.com
Project-URL: Documentation, https://gitlab.com/the-bootcamp-project/packages/gitpy
Project-URL: Repository, https://gitlab.com/the-bootcamp-project/packages/gitpy.git
